{
  "CNN": {
    "per_class": {
      "MEL": {
        "iou": 0.4647,
        "dice": 0.5912
      },
      "NV": {
        "iou": 0.3266,
        "dice": 0.4446
      },
      "BCC": {
        "iou": 0.2452,
        "dice": 0.3667
      },
      "AKIEC": {
        "iou": 0.3686,
        "dice": 0.5098
      },
      "BKL": {
        "iou": 0.3639,
        "dice": 0.4841
      },
      "DF": {
        "iou": 0.2983,
        "dice": 0.4261
      },
      "VASC": {
        "iou": 0.3086,
        "dice": 0.4252
      }
    },
    "overall": {
      "iou": 0.3427,
      "dice": 0.4629
    }
  },
  "ResNet-50": {
    "per_class": {
      "MEL": {
        "iou": 0.4521,
        "dice": 0.6085
      },
      "NV": {
        "iou": 0.4102,
        "dice": 0.5638
      },
      "BCC": {
        "iou": 0.456,
        "dice": 0.6103
      },
      "AKIEC": {
        "iou": 0.4133,
        "dice": 0.5643
      },
      "BKL": {
        "iou": 0.4331,
        "dice": 0.5882
      },
      "DF": {
        "iou": 0.5024,
        "dice": 0.6607
      },
      "VASC": {
        "iou": 0.396,
        "dice": 0.5312
      }
    },
    "overall": {
      "iou": 0.4207,
      "dice": 0.5745
    }
  },
  "Swin-T": {
    "per_class": {
      "MEL": {
        "iou": 0.1049,
        "dice": 0.1649
      },
      "NV": {
        "iou": 0.0419,
        "dice": 0.0711
      },
      "BCC": {
        "iou": 0.2203,
        "dice": 0.325
      },
      "AKIEC": {
        "iou": 0.1904,
        "dice": 0.2987
      },
      "BKL": {
        "iou": 0.1207,
        "dice": 0.1917
      },
      "DF": {
        "iou": 0.1487,
        "dice": 0.2348
      },
      "VASC": {
        "iou": 0.1123,
        "dice": 0.1787
      }
    },
    "overall": {
      "iou": 0.0737,
      "dice": 0.1186
    }
  },
  "CLIP": {
    "per_class": {
      "MEL": {
        "iou": 0.0037,
        "dice": 0.0072
      },
      "NV": {
        "iou": 0.0024,
        "dice": 0.0048
      },
      "BCC": {
        "iou": 0.0047,
        "dice": 0.0092
      },
      "AKIEC": {
        "iou": 0.0083,
        "dice": 0.0163
      },
      "BKL": {
        "iou": 0.0047,
        "dice": 0.0093
      },
      "DF": {
        "iou": 0.0071,
        "dice": 0.014
      },
      "VASC": {
        "iou": 0.0017,
        "dice": 0.0033
      }
    },
    "overall": {
      "iou": 0.0032,
      "dice": 0.0062
    }
  },
  "DermLIP": {
    "per_class": {
      "MEL": {
        "iou": 0.0034,
        "dice": 0.0068
      },
      "NV": {
        "iou": 0.0021,
        "dice": 0.0041
      },
      "BCC": {
        "iou": 0.004,
        "dice": 0.0079
      },
      "AKIEC": {
        "iou": 0.0061,
        "dice": 0.0121
      },
      "BKL": {
        "iou": 0.0041,
        "dice": 0.0081
      },
      "DF": {
        "iou": 0.0055,
        "dice": 0.0108
      },
      "VASC": {
        "iou": 0.0013,
        "dice": 0.0027
      }
    },
    "overall": {
      "iou": 0.0027,
      "dice": 0.0053
    }
  }
}